chemlg/__init__.py
chemlg/feasibility.py
chemlg/libgen.py
chemlg/notebooks/__init__.py
chemlg/notebooks/main.py
chemlg/templates/__init__.py
chemlg/templates/building_blocks.dat
chemlg/templates/config.dat
chemlg/templates/genetic_algorithm_config.dat
chemlg-0.9.data/scripts/chemlgshell
chemlg-0.9.dist-info/LICENSE
chemlg-0.9.dist-info/METADATA
chemlg-0.9.dist-info/WHEEL
chemlg-0.9.dist-info/top_level.txt
chemlg-0.9.dist-info/RECORD
